transparent_background/InSPyReNet.py
transparent_background/Remover.py
transparent_background/__init__.py
transparent_background/config.yaml
transparent_background/gui.py
transparent_background/utils.py
transparent_background/backbones/SwinTransformer.py
transparent_background/modules/attention_module.py
transparent_background/modules/context_module.py
transparent_background/modules/decoder_module.py
transparent_background/modules/layers.py
transparent_background-1.3.4.dist-info/licenses/LICENSE
transparent_background-1.3.4.dist-info/METADATA
transparent_background-1.3.4.dist-info/WHEEL
transparent_background-1.3.4.dist-info/entry_points.txt
transparent_background-1.3.4.dist-info/top_level.txt
transparent_background-1.3.4.dist-info/RECORD
