Metadata-Version: 2.4
Name: transparent-background
Version: 1.3.4
Summary: Make images with transparent background
Home-page: https://github.com/plemeri/transparent-background
Author: Taehun Kim
Author-email: taehoon1018@postech.ac.kr
Classifier: Programming Language :: Python :: 3
Classifier: License :: OSI Approved :: MIT License
Classifier: Operating System :: OS Independent
Requires-Python: >=3.8
License-File: LICENSE
Requires-Dist: torch>=1.7.1
Requires-Dist: torchvision>=0.8.2
Requires-Dist: opencv-python>=4.6.0.66
Requires-Dist: timm>=1.0.3
Requires-Dist: tqdm>=4.64.1
Requires-Dist: kornia>=0.5.4
Requires-Dist: gdown>=4.5.4
Requires-Dist: wget>=3.2
Requires-Dist: easydict>=1.10
Requires-Dist: pyyaml>=6.0
Requires-Dist: albumentations>=1.3.1
Requires-Dist: albucore>=0.0.16
Requires-Dist: pymatting>=1.1.13
Provides-Extra: webcam
Requires-Dist: pyvirtualcam>=0.6.0; extra == "webcam"
Provides-Extra: gui
Requires-Dist: flet>=0.23.1; extra == "gui"
Dynamic: author
Dynamic: author-email
Dynamic: classifier
Dynamic: description
Dynamic: description-content-type
Dynamic: home-page
Dynamic: license-file
Dynamic: provides-extra
Dynamic: requires-dist
Dynamic: requires-python
Dynamic: summary
